{"cameraMode":{"drawMode":0,"name":"Shaded","section":"Shading Mode"},"sceneLighting":true,"audioPlay":false,"sceneViewState":{"m_AlwaysRefresh":false,"showFog":true,"showSkybox":true,"showFlares":true,"showImageEffects":true,"showParticleSystems":true,"showVisualEffectGraphs":true,"m_FxEnabled":true},"in2DMode":false,"pivot":{"x":105.89942932128906,"y":-487.9693603515625,"z":-198.04490661621095},"rotation":{"x":0.11463508009910584,"y":0.8245018720626831,"z":-0.523964524269104,"w":0.18038392066955567},"size":284.37322998046877,"orthographic":false}